clarifai_protocol.cpython-311-darwin.so
clarifai_protocol.pyi
clarifai_protocol-0.0.34.dist-info/licenses/LICENSE
clarifai_protocol.build/.gitignore
clarifai_protocol-0.0.34.dist-info/METADATA
clarifai_protocol-0.0.34.dist-info/WHEEL
clarifai_protocol-0.0.34.dist-info/top_level.txt
clarifai_protocol-0.0.34.dist-info/RECORD
