Metadata-Version: 2.4
Name: clarifai-protocol
Version: 0.0.34
Summary: Clarifai Python Runner Protocol
Author-email: Clarifai <support@clarifai.com>
License:                                  Apache License
Project-URL: Repository, https://github.com/Clarifai/clarifai-protocol
Project-URL: Homepage, https://clarifai.com
Keywords: clarifai,runners,python
Classifier: Topic :: Scientific/Engineering :: Artificial Intelligence
Classifier: Programming Language :: Python :: 3
Classifier: Programming Language :: Python :: 3 :: Only
Classifier: Programming Language :: Python :: 3.9
Classifier: Programming Language :: Python :: 3.10
Classifier: Programming Language :: Python :: 3.11
Classifier: Programming Language :: Python :: 3.12
Classifier: Programming Language :: Python :: 3.13
Classifier: Programming Language :: Python :: Implementation :: CPython
Classifier: License :: OSI Approved :: Apache Software License
Classifier: Operating System :: OS Independent
Requires-Python: >=3.9
License-File: LICENSE
Requires-Dist: clarifai>=11.7.2
Requires-Dist: clarifai-grpc>=11.7.8
Dynamic: license-file
